courier/__init__.py
courier/libaddress_interceptor.so
courier/libclient.so
courier/libcourier_service_cc_grpc_proto.so
courier/libcourier_service_cc_proto.so
courier/libcourier_service_cc_proto_static.so
courier/librouter.so
courier/libtf_serialize.so
courier/handlers/libhandler_batcher.so
courier/handlers/libhelpers.so
courier/handlers/libpy_call.so
courier/handlers/python/pybind.so
courier/platform/default/libclient_monitor.so
courier/platform/default/libcourier_service_impl.so
courier/platform/default/libgrpc_utils.so
courier/platform/default/liblogging.so
courier/platform/default/libpy_utils.so
courier/platform/default/libserver.so
courier/platform/default/libstatus_macros.so
courier/python/client.py
courier/python/client_test.py
courier/python/libbatching.so
courier/python/libpy_serialize.so
courier/python/libpybind_serialize_pybind.so
courier/python/libserialization_cc_proto.so
courier/python/libserialization_cc_proto_static.so
courier/python/libtensor_conversion.so
courier/python/py_client.so
courier/python/py_server.py
courier/python/pybind.so
courier/python/router.so
courier/python/server.so
launchpad/__init__.py
launchpad/address.py
launchpad/context.py
launchpad/flags.py
launchpad/lazy_loader.py
launchpad/program.py
launchpad/program_test.py
launchpad/examples/__init__.py
launchpad/examples/batching/__init__.py
launchpad/examples/batching/launch.py
launchpad/examples/consumer_producers/__init__.py
launchpad/examples/consumer_producers/launch.py
launchpad/examples/consumer_producers/launch_test.py
launchpad/examples/consumer_producers/launch_vertex_ai.py
launchpad/examples/consumer_producers/program.py
launchpad/examples/consumer_producers/requirements.txt
launchpad/examples/hello_world/__init__.py
launchpad/examples/hello_world/launch.py
launchpad/examples/program_wait/__init__.py
launchpad/examples/program_wait/launch.py
launchpad/launch/__init__.py
launchpad/launch/launch.py
launchpad/launch/serialization.py
launchpad/launch/serialization_test.py
dm_launchpad_nightly-0.5.2.dev20230218.dist-info/LICENSE
dm_launchpad_nightly-0.5.2.dev20230218.dist-info/METADATA
dm_launchpad_nightly-0.5.2.dev20230218.dist-info/WHEEL
dm_launchpad_nightly-0.5.2.dev20230218.dist-info/top_level.txt
dm_launchpad_nightly-0.5.2.dev20230218.dist-info/RECORD
